viraxi/__init__.py
viraxi-0.0.1.dist-info/METADATA
viraxi-0.0.1.dist-info/WHEEL
viraxi-0.0.1.dist-info/top_level.txt
viraxi-0.0.1.dist-info/RECORD
