Metadata-Version: 2.4
Name: viraxi
Version: 0.0.1
Summary: Viraxi research toolkit.
Author: jassem-manita
Author-email: jasemmanita00@email.com
Requires-Python: >=3.10
Dynamic: author
Dynamic: author-email
Dynamic: description-content-type
Dynamic: requires-python
Dynamic: summary
